{
	"animations": [
		{
			"loop": false,
			"offsets": [
				-965,
				40
			],
			"anim": "idle",
			"fps": 24,
			"name": "idle",
			"indices": []
		},
		{
			"loop": false,
			"offsets": [
				-1125,
				34
			],
			"anim": "singLEFT",
			"fps": 24,
			"name": "left",
			"indices": []
		},
		{
			"loop": false,
			"offsets": [
				-1170,
				14
			],
			"anim": "singDOWN",
			"fps": 24,
			"name": "down",
			"indices": []
		},
		{
			"loop": false,
			"offsets": [
				-1176,
				37
			],
			"anim": "singUP",
			"fps": 24,
			"name": "up",
			"indices": []
		},
		{
			"loop": false,
			"offsets": [
				-1012,
				30
			],
			"anim": "singRIGHT",
			"fps": 24,
			"name": "right",
			"indices": []
		}
	],
	"no_antialiasing": false,
	"image": "characters/pibby",
	"position": [
		0,
		350
	],
	"healthicon": "pibby",
	"flip_x": false,
	"healthbar_colors": [
		180,
		135,
		135
	],
	"camera_position": [
		180,
		0
	],
	"sing_duration": 4,
	"scale": 1
}